PythonShujuKexueHeJiqiXuexiShijianZhinanChuyiFix1/README.md
PythonShujuKexueHeJiqiXuexiShijianZhinanChuyiFix1/__init__.py
PythonShujuKexueHeJiqiXuexiShijianZhinanChuyiFix1/__main__.py
PythonShujuKexueHeJiqiXuexiShijianZhinanChuyiFix1/file.epub
PythonShujuKexueHeJiqiXuexiShijianZhinanChuyiFix1/index.html
PythonShujuKexueHeJiqiXuexiShijianZhinanChuyiFix1/css/__init__.py
PythonShujuKexueHeJiqiXuexiShijianZhinanChuyiFix1/css/annotations.css
PythonShujuKexueHeJiqiXuexiShijianZhinanChuyiFix1/css/main.css
PythonShujuKexueHeJiqiXuexiShijianZhinanChuyiFix1/css/normalize.css
PythonShujuKexueHeJiqiXuexiShijianZhinanChuyiFix1/css/popup.css
PythonShujuKexueHeJiqiXuexiShijianZhinanChuyiFix1/font/__init__.py
PythonShujuKexueHeJiqiXuexiShijianZhinanChuyiFix1/font/fontello.eot
PythonShujuKexueHeJiqiXuexiShijianZhinanChuyiFix1/font/fontello.svg
PythonShujuKexueHeJiqiXuexiShijianZhinanChuyiFix1/font/fontello.ttf
PythonShujuKexueHeJiqiXuexiShijianZhinanChuyiFix1/font/fontello.woff
PythonShujuKexueHeJiqiXuexiShijianZhinanChuyiFix1/img/__init__.py
PythonShujuKexueHeJiqiXuexiShijianZhinanChuyiFix1/img/annotator-glyph-sprite.png
PythonShujuKexueHeJiqiXuexiShijianZhinanChuyiFix1/img/annotator-icon-sprite.png
PythonShujuKexueHeJiqiXuexiShijianZhinanChuyiFix1/img/apple-touch-icon.png
PythonShujuKexueHeJiqiXuexiShijianZhinanChuyiFix1/img/cancelfullscreen.png
PythonShujuKexueHeJiqiXuexiShijianZhinanChuyiFix1/img/close.png
PythonShujuKexueHeJiqiXuexiShijianZhinanChuyiFix1/img/fullscreen.png
PythonShujuKexueHeJiqiXuexiShijianZhinanChuyiFix1/img/loader.gif
PythonShujuKexueHeJiqiXuexiShijianZhinanChuyiFix1/img/menu-icon.png
PythonShujuKexueHeJiqiXuexiShijianZhinanChuyiFix1/img/save.png
PythonShujuKexueHeJiqiXuexiShijianZhinanChuyiFix1/img/saved.png
PythonShujuKexueHeJiqiXuexiShijianZhinanChuyiFix1/img/settings-s.png
PythonShujuKexueHeJiqiXuexiShijianZhinanChuyiFix1/img/settings.png
PythonShujuKexueHeJiqiXuexiShijianZhinanChuyiFix1/img/star.png
python_shuju_kexue_he_jiqi_xuexi_shijian_zhinan_chuyi_fix1-2025.3.25.1.dist-info/METADATA
python_shuju_kexue_he_jiqi_xuexi_shijian_zhinan_chuyi_fix1-2025.3.25.1.dist-info/WHEEL
python_shuju_kexue_he_jiqi_xuexi_shijian_zhinan_chuyi_fix1-2025.3.25.1.dist-info/entry_points.txt
python_shuju_kexue_he_jiqi_xuexi_shijian_zhinan_chuyi_fix1-2025.3.25.1.dist-info/top_level.txt
python_shuju_kexue_he_jiqi_xuexi_shijian_zhinan_chuyi_fix1-2025.3.25.1.dist-info/RECORD
